wallall/__init__.py
wallall/test.py
wallall/wallall.py
wallall-0.1.dist-info/DESCRIPTION.rst
wallall-0.1.dist-info/METADATA
wallall-0.1.dist-info/RECORD
wallall-0.1.dist-info/WHEEL
wallall-0.1.dist-info/metadata.json
wallall-0.1.dist-info/top_level.txt
