Metadata-Version: 2.0
Name: wallall
Version: 0.1
Summary: A wallall lib
Home-page: https://github.com/drbytes/wallall
Author: Yves Vanlerberghe
Author-email: yves@infothek.be
License: UNKNOWN
Download-URL: https://github.com/drbytes/wallall/archive/0.1.tar.gz
Keywords: wallall,control,tts
Platform: UNKNOWN
